testmz/__init__.py
testmz-0.1.dist-info/METADATA
testmz-0.1.dist-info/WHEEL
testmz-0.1.dist-info/top_level.txt
testmz-0.1.dist-info/RECORD
