Metadata-Version: 2.1
Name: testmz
Version: 0.1
Summary: The first python test package
Home-page: http://github.com/mudassir21/server
Author: Mudassir Zakaria
Author-email: mudassir21bd@gmail.com
License: MIT
Platform: UNKNOWN
